LICENSE.txt
MANIFEST.in
README.txt
setup.py
pcart_customers/__init__.py
pcart_customers/admin.py
pcart_customers/apps.py
pcart_customers/backend.py
pcart_customers/cms_apps.py
pcart_customers/forms.py
pcart_customers/models.py
pcart_customers/tasks.py
pcart_customers/urls.py
pcart_customers/utils.py
pcart_customers/views.py
pcart_customers.egg-info/PKG-INFO
pcart_customers.egg-info/SOURCES.txt
pcart_customers.egg-info/dependency_links.txt
pcart_customers.egg-info/not-zip-safe
pcart_customers.egg-info/requires.txt
pcart_customers.egg-info/top_level.txt
pcart_customers/locale/ru/LC_MESSAGES/django.mo
pcart_customers/locale/ru/LC_MESSAGES/django.po
pcart_customers/locale/uk/LC_MESSAGES/django.mo
pcart_customers/locale/uk/LC_MESSAGES/django.po
pcart_customers/migrations/0001_initial.py
pcart_customers/migrations/0002_auto_20170223_2055.py
pcart_customers/migrations/0003_passwordresetlink.py
pcart_customers/migrations/0004_auto_20170301_2010.py
pcart_customers/migrations/0005_productpagevisit.py
pcart_customers/migrations/0006_auto_20170408_1520.py
pcart_customers/migrations/0007_wishlistedproduct.py
pcart_customers/migrations/0008_comparisonproduct.py
pcart_customers/migrations/0009_auto_20170412_1252.py
pcart_customers/migrations/__init__.py
pcart_customers/templates/customers/admin/auth/user/add_form.html